zur_ecu_client/ecu_client.py
zur_ecu_client/messages.py
zur_ecu_client/mock_ecu.py
zur_ecu_client/udp_server.py
zur_ecu_client/senml/senml.py
zur_ecu_client/senml/senml_msg.py
zur_ecu_client/senml/senml_msg_ecu.py
zur_ecu_client/senml/senml_unit.py
zur_ecu_client/senml/senml_zur_names.py
zur_ecu_client/senml/util.py
zur_ecu_client-0.2.0.dist-info/METADATA
zur_ecu_client-0.2.0.dist-info/WHEEL
zur_ecu_client-0.2.0.dist-info/entry_points.txt
zur_ecu_client-0.2.0.dist-info/licenses/LICENSE.txt
zur_ecu_client-0.2.0.dist-info/RECORD
