Metadata-Version: 2.3
Name: zur_ecu_client
Version: 0.2.0
Summary: Internal Python library which provides an interface to the ECU
Project-URL: Homepage, https://zurichuasracing.ch
Project-URL: Bug Reports, https://github.com/zurich-uas-racing/issues
Project-URL: Source, https://github.com/zurich-uas-racing/ecu-client
Author-email: ZUR Driverless <driverless@zurichuasracing.ch>, Finn Scheller <finn.scheller@zurichuasracing.ch>, Cèline Brun <bruncel1@students.zhaw.ch>
Maintainer-email: ZUR Driverless <driverless@zurichuasracing.ch>
License: MIT License
Keywords: development,sample,setuptools
Classifier: Development Status :: 3 - Alpha
Classifier: Intended Audience :: Developers
Classifier: License :: OSI Approved :: MIT License
Classifier: Programming Language :: Python :: 3
Classifier: Programming Language :: Python :: 3 :: Only
Classifier: Programming Language :: Python :: 3.8
Classifier: Programming Language :: Python :: 3.9
Classifier: Programming Language :: Python :: 3.10
Classifier: Programming Language :: Python :: 3.11
Classifier: Programming Language :: Python :: 3.12
Classifier: Topic :: Software Development :: Build Tools
Requires-Python: >=3.8
Requires-Dist: pyyaml
Provides-Extra: dev
Requires-Dist: check-manifest; extra == 'dev'
Provides-Extra: test
Requires-Dist: coverage; extra == 'test'
